{
  "networks": {
    "emulator": "127.0.0.1:3569",
    "mainnet": "access.mainnet.nodes.onflow.org:9000",
    "sandboxnet": "access.sandboxnet.nodes.onflow.org:9000",
    "testnet": "access.devnet.nodes.onflow.org:9000"
  },
  "accounts": {
    "emulator-account": {
      "address": "f8d6e0586b0a20c7",
      "key": "cf141d995afb2971958f2f0e914fd763bb62ee3ca8e948b56eb91ee2ad62e2cf"
    }
  },
  "contracts": {
    "ISPOManager": "./cadence/contracts/ISPOManager.cdc",
    "FungibleToken": {
      "source": "./cadence/contracts/standard/FungibleToken.cdc",
      "aliases": {
        "testnet": "0x9a0766d93b6608b7",
        "emulator": "0xee82856bf20e2aa6",
        "mainnet": "0xf233dcee88fe0abe"
      }
    }
  },
  "deployments": {
    "emulator": {
      "emulator-account": ["ISPOManager"]
    }
  }
}
